anyquote/__init__.py
anyquote/font_manager.py
anyquote/internet/__init__.py
anyquote/internet/twi.py
anyquote/rander/__init__.py
anyquote/rander/img.py
anyquote/rander/text.py
anyquote-0.3.11.dist-info/LICENSE
anyquote-0.3.11.dist-info/METADATA
anyquote-0.3.11.dist-info/WHEEL
anyquote-0.3.11.dist-info/RECORD
