Metadata-Version: 2.1
Name: anyquote
Version: 0.3.11
Summary: 
Author: hsn
Author-email: hsn1919810@gmail.com
Requires-Python: >=3.11,<4.0
Classifier: Programming Language :: Python :: 3
Classifier: Programming Language :: Python :: 3.11
Classifier: Programming Language :: Python :: 3.12
Requires-Dist: fonttools (>=4.53.1,<5.0.0)
Requires-Dist: pillow (>=10.4.0,<11.0.0)
Requires-Dist: playwright (>=1.47.0,<2.0.0)
Requires-Dist: qrcode (>=7.4.2,<8.0.0)
Requires-Dist: requests (>=2.32.3,<3.0.0)
Requires-Dist: rich (>=13.9.3,<14.0.0)
Requires-Dist: twitter-api-client (>=0.10.22,<0.11.0)
